dbest_sdk/__init__.py
dbest_sdk/core.py
dbest_sdk/serial_broker.py
dbest_sdk/server.py
dbest_sdk/autogen/__init__.py
dbest_sdk/autogen/bidirectional_pb2.py
dbest_sdk/autogen/bidirectional_pb2_grpc.py
dbest_sdk-0.1.1.dist-info/AUTHORS.rst
dbest_sdk-0.1.1.dist-info/LICENSE
dbest_sdk-0.1.1.dist-info/METADATA
dbest_sdk-0.1.1.dist-info/WHEEL
dbest_sdk-0.1.1.dist-info/top_level.txt
dbest_sdk-0.1.1.dist-info/RECORD
