Metadata-Version: 2.1
Name: dbest-sdk
Version: 0.1.1
Summary: A Python package for remote control of DBEST (drone battery exchanger system for DJI Mavic 2 products)
Home-page: https://github.com/PSBPOSAS/dbest-sdk
Author: IoTDeco
Author-email: contacto@iotdeco.com
License: MIT license
Keywords: dbest,sdk,dji,mavic,battery,exchanger,robotic
Platform: UNKNOWN
Classifier: Development Status :: 2 - Pre-Alpha
Classifier: Intended Audience :: Developers
Classifier: License :: OSI Approved :: MIT License
Classifier: Natural Language :: English
Classifier: Programming Language :: Python :: 3.8
Requires-Python: >=3.5
Requires-Dist: janus (==0.5.0)
Requires-Dist: grpcio (==1.30.0)
Requires-Dist: grpcio-tools (==1.30.0)
Requires-Dist: pyserial (==3.4)
